broadlink_listener/__init__.py
broadlink_listener/cli_tools/__init__.py
broadlink_listener/cli_tools/broadlink_manager.py
broadlink_listener/cli_tools/cli.py
broadlink_listener/cli_tools/smartir_manager.py
broadlink_listener/cli_tools/utils.py
broadlink_listener/py.typed
broadlink_listener/py.typed.license
broadlink_listener-1.2.0.dist-info/WHEEL
broadlink_listener-1.2.0.dist-info/METADATA
broadlink_listener-1.2.0.dist-info/entry_points.txt
broadlink_listener-1.2.0.dist-info/LICENSES/MIT.txt
broadlink_listener-1.2.0.dist-info/RECORD
