Metadata-Version: 2.1
Name: broadlink-listener
Version: 1.2.0
Summary: Broadlink IR codes listener and SmartIR json generator.
Home-page: https://github.com/gpongelli/broadlink-listener
License: MIT
Author: Gabriele Pongelli
Author-email: gabriele.pongelli@gmail.com
Requires-Python: >=3.8.0,<4.0
Classifier: Development Status :: 5 - Production/Stable
Classifier: Intended Audience :: Developers
Classifier: License :: OSI Approved :: MIT License
Classifier: Natural Language :: English
Classifier: Programming Language :: Python :: 3
Classifier: Programming Language :: Python :: 3.8
Classifier: Programming Language :: Python :: 3.9
Classifier: Programming Language :: Python :: 3.10
Classifier: Programming Language :: Python :: 3.11
Classifier: Programming Language :: Python :: 3
Classifier: Programming Language :: Python :: 3.10
Classifier: Programming Language :: Python :: 3.11
Classifier: Programming Language :: Python :: 3.8
Classifier: Programming Language :: Python :: 3.9
Requires-Dist: broadlink (>=0.18.3,<0.19.0)
Requires-Dist: click (==8.1.3)
Requires-Dist: cloup (>=2.0.0,<3.0.0)
Requires-Dist: termcolor (>=2.1.1,<3.0.0)
Requires-Dist: tqdm (>=4.64.0,<5.0.0)
